LICENSE
p115filedb/__init__.py
p115filedb/__main__.py
p115filedb/py.typed
p115filedb/updatedb.py
p115filedb-0.0.3.dist-info/LICENSE
p115filedb-0.0.3.dist-info/LICENSE_zh
p115filedb-0.0.3.dist-info/METADATA
p115filedb-0.0.3.dist-info/WHEEL
p115filedb-0.0.3.dist-info/entry_points.txt
p115filedb-0.0.3.dist-info/RECORD
