Metadata-Version: 2.1
Name: p115filedb
Version: 0.0.3
Summary: 把 115 网盘的文件列表导出到数据库（仅文件）
Home-page: https://github.com/ChenyangGao/p115client/tree/main/modules/p115filedb
License: MIT
Keywords: python-115,updatedb
Author: ChenyangGao
Author-email: wosiwujm@gmail.com
Requires-Python: >=3.12,<4.0
Classifier: Development Status :: 5 - Production/Stable
Classifier: Intended Audience :: Developers
Classifier: License :: OSI Approved :: MIT License
Classifier: Operating System :: OS Independent
Classifier: Programming Language :: Python
Classifier: Programming Language :: Python :: 3
Classifier: Programming Language :: Python :: 3.12
Classifier: Programming Language :: Python :: 3.13
Classifier: Programming Language :: Python :: 3 :: Only
Classifier: Topic :: Software Development
Classifier: Topic :: Software Development :: Libraries
Classifier: Topic :: Software Development :: Libraries :: Python Modules
Requires-Dist: orjson
Requires-Dist: p115client (>=0.0.5.5.4.1)
Requires-Dist: python-concurrenttools (>=0.0.8.2)
Requires-Dist: sqlitetools (>=0.0.2.1)
Project-URL: Repository, https://github.com/ChenyangGao/p115client/tree/main/modules/p115filedb
